[
  {
    "Id": "325c4615",
    "Visiblity": 1,
    "Receiver": "Worker",
    "Sender": "Employer",
    "Time": "2024-03-31T14:06:31.5119656+04:00",
    "WorkId": null,
    "HTML": "\r\n<!DOCTYPE html>\r\n<html lang=\"en\">\r\n<head>\r\n    <meta charset=\"UTF-8\">\r\n    <meta name=\"viewport\" content=\"width=device-width, initial-scale=1.0\">\r\n    <title>Job Invitation Email</title>\r\n    <style>\r\n        body {\r\n            font-family: Arial, sans-serif;\r\n            background-color: #f9f9f9;\r\n            color: #333;\r\n        }\r\n        h1 {\r\n            color: #0074d9;\r\n            margin-bottom: 20px;\r\n        }\r\n        p {\r\n            font-size: 16px;\r\n            line-height: 1.6;\r\n            margin-bottom: 15px;\r\n        }\r\n        ul {\r\n            list-style-type: disc;\r\n            margin-left: 20px;\r\n        }\r\n        footer {\r\n            font-size: 14px;\r\n            color: #888;\r\n            margin-top: 30px;\r\n        }\r\n    </style>\r\n</head>\r\n<body>\r\n    <h1>Dear Worker,</h1>\r\n    <p>We are pleased to extend this invitation to you to join our <strong> IT Comp</strong>.</p>\r\n    <p>Your skills and experience align perfectly with what we are looking for, and we believe that you would be a valuable addition to our team. <strong>IT Comp</strong> is dedicated to connecting talented individuals like yourself with meaningful job opportunities.</p>\r\n    <p>As a member of our program, you will have access to a wide range of job listings and resources designed to help you succeed in your career.</p>\r\n    <p>Here are some key benefits of joining <strong>IT Comp</strong>:</p>\r\n    <ul>\r\n        <li>Job Opportunities: Gain access to a diverse range of job listings tailored to your skills and preferences.</li>\r\n        <li>Networking: Connect with industry professionals and expand your professional network.</li>\r\n        <li>Career Development: Access resources and training materials to enhance your skills and advance your career.</li>\r\n        <li>Flexibility: Enjoy the flexibility to choose the jobs that best fit your schedule and career goals.</li>\r\n    </ul>\r\n    <p>We are excited about the opportunity to work with you and help you achieve your career aspirations. If you have any questions or need further information, please don't hesitate to contact us. We look forward to welcoming you to <strong>IT Comp</strong>!</p>\r\n    <footer>\r\n        Sincerely,<br>\r\n                   Employer<br>\r\n        31.3.2024<br>\r\n        Contact Information:<br>\r\n        Email: qasimov.vaqif512@gmail.com<br>\r\n        Phone: 55 555 55 55<br>\r\n        City: Baku\r\n    </footer>\r\n</body>\r\n</html>\r\n",
    "Content": "\r\n\r\n    Worker\r\n    Shamkkir ZIP: AZ-057\r\n    \r\n    Dear Worker,\r\n    We are pleased to extend this invitation to you to join our IT Comp. \r\n    \r\n    Your skills and experience align perfectly with what we are looking for, and we believe that you would be a valuable addition to our team.\r\n    IT Comp is dedicated to connecting talented individuals like yourself with meaningful job opportunities. \r\n    As a member of our program, you will have access to a wide range of job listings and resources designed to help you succeed in your career.\r\n    \r\n    Here are some key benefits of joining IT Comp:\r\n    \r\n    Job Opportunities: Gain access to a diverse range of job listings tailored to your skills and preferences.\r\n    Networking: Connect with industry professionals and expand your professional network.\r\n    Career Development: Access resources and training materials to enhance your skills and advance your career.\r\n    Flexibility: Enjoy the flexibility to choose the jobs that best fit your schedule and career goals.\r\n    \r\n    We are excited about the opportunity to work with you and help you achieve your career aspirations. \r\n    If you have any questions or need further information, please don't hesitate to contact us.\r\n    We look forward to welcoming you to IT Comp!\r\n    \r\n    Sincerely,\r\n    Employer                                  31.3.2024 \r\n    \r\n    qasimov.vaqif512@gmail.com\r\n    55 555 55 55\r\n    Baku"
  },
  {
    "Id": "c77f7f15",
    "Visiblity": 1,
    "Receiver": "Employer",
    "Sender": "Worker",
    "Time": "2024-03-31T14:07:29.2485231+04:00",
    "WorkId": "0dba9b1a",
    "HTML": "\r\n               <!DOCTYPE html>\r\n                <html lang=\"en\">\r\n                <head>\r\n                    <meta charset=\"UTF-8\">\r\n                    <meta name=\"viewport\" content=\"width=device-width, initial-scale=1.0\">\r\n                    <title>Job Application Email</title>\r\n                    <style>\r\n                        body {\r\n                            font-family: Arial, sans-serif;\r\n                            background-color: #f9f9f9;\r\n                            color: #333;\r\n                            margin: 0;\r\n                            padding: 0;\r\n                        }\r\n                        .container {\r\n                            max-width: 600px;\r\n                            margin: 0 auto;\r\n                            padding: 20px;\r\n                        }\r\n                        h1 {\r\n                            color: #0074d9;\r\n                            margin-bottom: 20px;\r\n                        }\r\n                        p {\r\n                            font-size: 16px;\r\n                            line-height: 1.6;\r\n                            margin-bottom: 15px;\r\n                        }\r\n                        strong {\r\n                            color: #2ecc40;\r\n                        }\r\n                        footer {\r\n                            font-size: 14px;\r\n                            color: #888;\r\n                            margin-top: 30px;\r\n                        }\r\n                    </style>\r\n                </head>\r\n                <body>\r\n                    <div class=\"container\">\r\n                        <h1>Hello Employer,</h1>\r\n                        <p>I am writing to express my interest in the <strong>asdasdasd</strong> advertised by <strong>sadasd</strong>. With my experience and qualifications, I am confident in my ability to contribute effectively to your team.</p>\r\n                        <p>I am particularly drawn to specific aspects of the job, and I am excited about the opportunity to [mention what you hope to achieve or contribute]. Through my previous experience in [mention relevant experience or projects], I have developed a strong foundation in [mention relevant skills or competencies] that align well with the requirements of the position.</p>\r\n                        <p>I am eager to bring my skills or qualities to <strong>sadasd</strong> and to further develop my abilities.</p>\r\n                        <p>Enclosed is my CV, which provides additional details about my background and accomplishments. I would welcome the opportunity to discuss how my skills and experiences align with the needs of your team. Please feel free to contact me at your convenience to schedule a meeting or interview.</p>\r\n                        <p>Thank you for considering my application. I look forward to the possibility of contributing to <strong>sadasd</strong>.</p>\r\n                        <footer>\r\n                            Sincerely,<br>\r\n                            Worker<br>\r\n                            qasimov.vaqif512@gmail.com<br>\r\n                            55 555 55 55<br><br>\r\n                   <p> You can find my CV below:</p><br>\r\n                  <p>School:  3 \r\nPoint: 555\r\nSpeciality: Programmer\r\nUniversity: ASOIU\r\n\r\nSkills:\r\n* C++\r\n* Java\r\n* C#\r\nLanguages:\r\n* English (A2)\r\nCompanies:\r\n* IT tech (2 years)\r\n</p>\r\n                        </footer>\r\n                    </div>\r\n                </body>\r\n                </html>",
    "Content": "\r\n    Worker\r\n    Shamkkir ZIP Code: AZ-057\r\n    qasimov.vaqif512@gmail.com\r\n    55 555 55 55\r\n    31.3.2024\r\n    \r\n    \r\n    Dear Employer,\r\n    \r\n    I am writing to express my interest in the asdasdasd advertised by sadasd. \r\n    With my experience, and qualifications, I am confident in my ability to contribute effectively to your team.\r\n    \r\n    I am particularly drawn to  specific aspects of the job  and I am excited about the opportunity to [mention what  you    hope to achieve or contribute]. Through my previous experience in [mention relevant experience or projects], I have developed a strong  foundation in    [mention relevant skills or competencies] that align well with the requirements of the position.\r\n    \r\n    I am eager to bring my skills or qualities to sadasd and to further develop my abilities.\r\n    \r\n    Enclosed is my CV, which provides additional details about my background and accomplishments. I would welcome the opportunity to discuss how my     skills and experiences align with the needs of your team. Please feel free to contact me at your convenience to schedule a meeting or interview.\r\n    \r\n    Thank you for considering my application. I look forward to the possibility of contributing to sadasd.\r\n    \r\n    Sincerely,\r\n    \r\n    Worker\r\n\r\n\r\nPlease find below my CV:\r\n\r\n\r\nSchool:  3 \r\nPoint: 555\r\nSpeciality: Programmer\r\nUniversity: ASOIU\r\n\r\nSkills:\r\n* C++\r\n* Java\r\n* C#\r\nLanguages:\r\n* English (A2)\r\nCompanies:\r\n* IT tech (2 years)\r\n"
  },
  {
    "Id": "9c23f18d",
    "Visiblity": 1,
    "Receiver": "Employer",
    "Sender": "Worker",
    "Time": "2024-03-31T14:20:36.786073+04:00",
    "WorkId": "0dba9b1a",
    "HTML": "\r\n               <!DOCTYPE html>\r\n                <html lang=\"en\">\r\n                <head>\r\n                    <meta charset=\"UTF-8\">\r\n                    <meta name=\"viewport\" content=\"width=device-width, initial-scale=1.0\">\r\n                    <title>Job Application Email</title>\r\n                    <style>\r\n                        body {\r\n                            font-family: Arial, sans-serif;\r\n                            background-color: #f9f9f9;\r\n                            color: #333;\r\n                            margin: 0;\r\n                            padding: 0;\r\n                        }\r\n                        .container {\r\n                            max-width: 600px;\r\n                            margin: 0 auto;\r\n                            padding: 20px;\r\n                        }\r\n                        h1 {\r\n                            color: #0074d9;\r\n                            margin-bottom: 20px;\r\n                        }\r\n                        p {\r\n                            font-size: 16px;\r\n                            line-height: 1.6;\r\n                            margin-bottom: 15px;\r\n                        }\r\n                        strong {\r\n                            color: #2ecc40;\r\n                        }\r\n                        footer {\r\n                            font-size: 14px;\r\n                            color: #888;\r\n                            margin-top: 30px;\r\n                        }\r\n                    </style>\r\n                </head>\r\n                <body>\r\n                    <div class=\"container\">\r\n                        <h1>Hello Employer,</h1>\r\n                        <p>I am writing to express my interest in the <strong>asdasdasd</strong> advertised by <strong>sadasd</strong>. With my experience and qualifications, I am confident in my ability to contribute effectively to your team.</p>\r\n                        <p>I am particularly drawn to specific aspects of the job, and I am excited about the opportunity to [mention what you hope to achieve or contribute]. Through my previous experience in [mention relevant experience or projects], I have developed a strong foundation in [mention relevant skills or competencies] that align well with the requirements of the position.</p>\r\n                        <p>I am eager to bring my skills or qualities to <strong>sadasd</strong> and to further develop my abilities.</p>\r\n                        <p>Enclosed is my CV, which provides additional details about my background and accomplishments. I would welcome the opportunity to discuss how my skills and experiences align with the needs of your team. Please feel free to contact me at your convenience to schedule a meeting or interview.</p>\r\n                        <p>Thank you for considering my application. I look forward to the possibility of contributing to <strong>sadasd</strong>.</p>\r\n                        <footer>\r\n                            Sincerely,<br>\r\n                            Worker<br>\r\n                            qasimov.vaqif512@gmail.com<br>\r\n                            55 555 55 55<br><br>\r\n                   <p> You can find my CV below:</p><br>\r\n                  <p>School:  3 \r\nPoint: 555\r\nSpeciality: Programmer\r\nUniversity: ASOIU\r\n\r\nSkills:\r\n* C++\r\n* Java\r\n* C#\r\nLanguages:\r\n* English (A2)\r\nCompanies:\r\n* IT tech (2 years)\r\n</p>\r\n                        </footer>\r\n                    </div>\r\n                </body>\r\n                </html>",
    "Content": "\r\n    Worker\r\n    Shamkkir ZIP Code: AZ-057\r\n    qasimov.vaqif512@gmail.com\r\n    55 555 55 55\r\n    31.3.2024\r\n    \r\n    \r\n    Dear Employer,\r\n    \r\n    I am writing to express my interest in the asdasdasd advertised by sadasd. \r\n    With my experience, and qualifications, I am confident in my ability to contribute effectively to your team.\r\n    \r\n    I am particularly drawn to  specific aspects of the job  and I am excited about the opportunity to [mention what  you    hope to achieve or contribute]. Through my previous experience in [mention relevant experience or projects], I have developed a strong  foundation in    [mention relevant skills or competencies] that align well with the requirements of the position.\r\n    \r\n    I am eager to bring my skills or qualities to sadasd and to further develop my abilities.\r\n    \r\n    Enclosed is my CV, which provides additional details about my background and accomplishments. I would welcome the opportunity to discuss how my     skills and experiences align with the needs of your team. Please feel free to contact me at your convenience to schedule a meeting or interview.\r\n    \r\n    Thank you for considering my application. I look forward to the possibility of contributing to sadasd.\r\n    \r\n    Sincerely,\r\n    \r\n    Worker\r\n\r\n\r\nPlease find below my CV:\r\n\r\n\r\nSchool:  3 \r\nPoint: 555\r\nSpeciality: Programmer\r\nUniversity: ASOIU\r\n\r\nSkills:\r\n* C++\r\n* Java\r\n* C#\r\nLanguages:\r\n* English (A2)\r\nCompanies:\r\n* IT tech (2 years)\r\n"
  },
  {
    "Id": "80d4d6ea",
    "Visiblity": 0,
    "Receiver": "Employer",
    "Sender": "Worker",
    "Time": "2024-03-31T14:27:13.7949918+04:00",
    "WorkId": "0dba9b1a",
    "HTML": "\r\n               <!DOCTYPE html>\r\n                <html lang=\"en\">\r\n                <head>\r\n                    <meta charset=\"UTF-8\">\r\n                    <meta name=\"viewport\" content=\"width=device-width, initial-scale=1.0\">\r\n                    <title>Job Application Email</title>\r\n                    <style>\r\n                        body {\r\n                            font-family: Arial, sans-serif;\r\n                            background-color: #f9f9f9;\r\n                            color: #333;\r\n                            margin: 0;\r\n                            padding: 0;\r\n                        }\r\n                        .container {\r\n                            max-width: 600px;\r\n                            margin: 0 auto;\r\n                            padding: 20px;\r\n                        }\r\n                        h1 {\r\n                            color: #0074d9;\r\n                            margin-bottom: 20px;\r\n                        }\r\n                        p {\r\n                            font-size: 16px;\r\n                            line-height: 1.6;\r\n                            margin-bottom: 15px;\r\n                        }\r\n                        strong {\r\n                            color: #2ecc40;\r\n                        }\r\n                        footer {\r\n                            font-size: 14px;\r\n                            color: #888;\r\n                            margin-top: 30px;\r\n                        }\r\n                    </style>\r\n                </head>\r\n                <body>\r\n                    <div class=\"container\">\r\n                        <h1>Hello Employer,</h1>\r\n                        <p>I am writing to express my interest in the <strong>asdasdasd</strong> advertised by <strong>sadasd</strong>. With my experience and qualifications, I am confident in my ability to contribute effectively to your team.</p>\r\n                        <p>I am particularly drawn to specific aspects of the job, and I am excited about the opportunity to [mention what you hope to achieve or contribute]. Through my previous experience in [mention relevant experience or projects], I have developed a strong foundation in [mention relevant skills or competencies] that align well with the requirements of the position.</p>\r\n                        <p>I am eager to bring my skills or qualities to <strong>sadasd</strong> and to further develop my abilities.</p>\r\n                        <p>Enclosed is my CV, which provides additional details about my background and accomplishments. I would welcome the opportunity to discuss how my skills and experiences align with the needs of your team. Please feel free to contact me at your convenience to schedule a meeting or interview.</p>\r\n                        <p>Thank you for considering my application. I look forward to the possibility of contributing to <strong>sadasd</strong>.</p>\r\n                        <footer>\r\n                            Sincerely,<br>\r\n                            Worker<br>\r\n                            qasimov.vaqif512@gmail.com<br>\r\n                            55 555 55 55<br><br>\r\n                   <p> You can find my CV below:</p><br>\r\n                  <p>School:  3 \r\nPoint: 555\r\nSpeciality: Programmer\r\nUniversity: ASOIU\r\n\r\nSkills:\r\n* C++\r\n* Java\r\n* C#\r\nLanguages:\r\n* English (A2)\r\nCompanies:\r\n* IT tech (2 years)\r\n</p>\r\n                        </footer>\r\n                    </div>\r\n                </body>\r\n                </html>",
    "Content": "\r\n    Worker\r\n    Shamkkir ZIP Code: AZ-057\r\n    qasimov.vaqif512@gmail.com\r\n    55 555 55 55\r\n    31.3.2024\r\n    \r\n    \r\n    Dear Employer,\r\n    \r\n    I am writing to express my interest in the asdasdasd advertised by sadasd. \r\n    With my experience, and qualifications, I am confident in my ability to contribute effectively to your team.\r\n    \r\n    I am particularly drawn to  specific aspects of the job  and I am excited about the opportunity to [mention what  you    hope to achieve or contribute]. Through my previous experience in [mention relevant experience or projects], I have developed a strong  foundation in    [mention relevant skills or competencies] that align well with the requirements of the position.\r\n    \r\n    I am eager to bring my skills or qualities to sadasd and to further develop my abilities.\r\n    \r\n    Enclosed is my CV, which provides additional details about my background and accomplishments. I would welcome the opportunity to discuss how my     skills and experiences align with the needs of your team. Please feel free to contact me at your convenience to schedule a meeting or interview.\r\n    \r\n    Thank you for considering my application. I look forward to the possibility of contributing to sadasd.\r\n    \r\n    Sincerely,\r\n    \r\n    Worker\r\n\r\n\r\nPlease find below my CV:\r\n\r\n\r\nSchool:  3 \r\nPoint: 555\r\nSpeciality: Programmer\r\nUniversity: ASOIU\r\n\r\nSkills:\r\n* C++\r\n* Java\r\n* C#\r\nLanguages:\r\n* English (A2)\r\nCompanies:\r\n* IT tech (2 years)\r\n"
  }
]